{
  "denominators": {
    "hard_zero (loop0 raw==0)": 243,
    "first_solved_loop1 (loop0==0 & loop1 raw>=1)  [n=37]": 37,
    "  of which loop1 raw==1  [= discovered_raw n=18]": 18,
    "  of which loop1 raw>=2": 19,
    "native_raw_1 (loop0 raw==1)": 52,
    "native_canon_1 (loop0 canon==1)": 56,
    "discovered_canon_0to1 (loop0 canon==0 & loop1 canon==1)": 18,
    "overlap disc_raw & disc_canon": 18
  },
  "groups": {
    "A_raw_native1 (loop0 raw==1 -> loop1)": {
      "n": 52,
      "retention": 0.827,
      "p_drop_to_0": 0.173,
      "p_add_raw": 0.75,
      "p_add_canon": 0.712,
      "mean_next_raw": 3.712,
      "mean_next_canon": 3.077,
      "median_next_canon": 3.0,
      "next_raw_bucket_dist": {
        "0": 0.173,
        "1": 0.077,
        "2-4": 0.404,
        "5-8": 0.288,
        "9-15": 0.058,
        "16": 0.0
      },
      "next_canon_bucket_dist": {
        "0": 0.173,
        "1": 0.115,
        "2-4": 0.481,
        "5-8": 0.212,
        "9-15": 0.019,
        "16": 0.0
      }
    },
    "B_raw_discovered0to1 (loop0==0,loop1 raw==1 -> loop2)": {
      "n": 18,
      "retention": 0.778,
      "p_drop_to_0": 0.222,
      "p_add_raw": 0.611,
      "p_add_canon": 0.611,
      "mean_next_raw": 2.778,
      "mean_next_canon": 2.444,
      "median_next_canon": 2.5,
      "next_raw_bucket_dist": {
        "0": 0.222,
        "1": 0.167,
        "2-4": 0.389,
        "5-8": 0.222,
        "9-15": 0.0,
        "16": 0.0
      },
      "next_canon_bucket_dist": {
        "0": 0.222,
        "1": 0.167,
        "2-4": 0.5,
        "5-8": 0.111,
        "9-15": 0.0,
        "16": 0.0
      }
    },
    "A_canon_native1 (loop0 canon==1 -> loop1)": {
      "n": 56,
      "retention": 0.839,
      "p_drop_to_0": 0.161,
      "p_add_raw": 0.768,
      "p_add_canon": 0.679,
      "mean_next_raw": 4.393,
      "mean_next_canon": 2.982,
      "median_next_canon": 3.0,
      "next_raw_bucket_dist": {
        "0": 0.161,
        "1": 0.071,
        "2-4": 0.375,
        "5-8": 0.286,
        "9-15": 0.071,
        "16": 0.036
      },
      "next_canon_bucket_dist": {
        "0": 0.161,
        "1": 0.161,
        "2-4": 0.464,
        "5-8": 0.196,
        "9-15": 0.018,
        "16": 0.0
      }
    },
    "B_canon_discovered0to1 (loop0 canon==0,loop1 canon==1 -> loop2)": {
      "n": 18,
      "retention": 0.778,
      "p_drop_to_0": 0.222,
      "p_add_raw": 0.611,
      "p_add_canon": 0.611,
      "mean_next_raw": 2.778,
      "mean_next_canon": 2.444,
      "median_next_canon": 2.5,
      "next_raw_bucket_dist": {
        "0": 0.222,
        "1": 0.167,
        "2-4": 0.389,
        "5-8": 0.222,
        "9-15": 0.0,
        "16": 0.0
      },
      "next_canon_bucket_dist": {
        "0": 0.222,
        "1": 0.167,
        "2-4": 0.5,
        "5-8": 0.111,
        "9-15": 0.0,
        "16": 0.0
      }
    }
  },
  "similarity": {
    "raw_buckets (A_raw vs B_raw)": {
      "obs_TV": 0.139,
      "TV_boot_mean": 0.237,
      "TV_95CI": [
        0.085,
        0.427
      ],
      "mean_canon_diff_A_minus_B": 0.632,
      "mean_canon_diff_95CI": [
        -0.507,
        1.703
      ],
      "perm_pvalue_mean_canon_diff": 0.321
    },
    "canon_buckets (A_canon vs B_canon)": {
      "obs_TV": 0.103,
      "TV_boot_mean": 0.207,
      "TV_95CI": [
        0.067,
        0.383
      ],
      "mean_canon_diff_A_minus_B": 0.538,
      "mean_canon_diff_95CI": [
        -0.583,
        1.567
      ],
      "perm_pvalue_mean_canon_diff": 0.38
    }
  }
}